embed/__init__.py
embed/__main__.py
embed_service-0.1.0.dist-info/LICENSE
embed_service-0.1.0.dist-info/METADATA
embed_service-0.1.0.dist-info/WHEEL
embed_service-0.1.0.dist-info/entry_points.txt
embed_service-0.1.0.dist-info/top_level.txt
embed_service-0.1.0.dist-info/RECORD
